zuraaaVoteChecker/__init__.py
zuraaaVoteChecker/cog.py
zuraaa_vote_checker-0.1.3.dist-info/LICENSE
zuraaa_vote_checker-0.1.3.dist-info/METADATA
zuraaa_vote_checker-0.1.3.dist-info/WHEEL
zuraaa_vote_checker-0.1.3.dist-info/top_level.txt
zuraaa_vote_checker-0.1.3.dist-info/RECORD
