Metadata-Version: 2.1
Name: zuraaa-vote-checker
Version: 0.1.3
Summary: Um coletor de votos no Zuraaa.
Home-page: https://github.com/uKaigo/zuraaa-vote-checker
Author: uKaigo
License: MIT
Project-URL: Issues, https://github.com/uKaigo/zuraaa-vote-checker/issues
Platform: UNKNOWN
Classifier: Development Status :: 5 - Production/Stable
Classifier: License :: OSI Approved :: MIT License
Classifier: Intended Audience :: Developers
Classifier: Natural Language :: Portuguese
Classifier: Operating System :: OS Independent
Classifier: Programming Language :: Python :: 3.6
Classifier: Programming Language :: Python :: 3.7
Classifier: Programming Language :: Python :: 3.8
Classifier: Topic :: Internet
Classifier: Topic :: Utilities
Requires-Python: >=3.5.3
Requires-Dist: discord.py (<=2.0.0,>=1.0.0)
